README.md
setup.py
moja_paczka/__init__.py
moja_paczka1.egg-info/PKG-INFO
moja_paczka1.egg-info/SOURCES.txt
moja_paczka1.egg-info/dependency_links.txt
moja_paczka1.egg-info/top_level.txt