Metadata-Version: 2.4
Name: moja_paczka1
Version: 0.1
Summary: sigma packages
Author: Sigma
Dynamic: author
Dynamic: summary
